gogaku_dl/__init__.py
gogaku_dl/english.py
gogaku_dl/gogaku_dl.py
gogaku_dl-0.1.1.dist-info/LICENSE
gogaku_dl-0.1.1.dist-info/METADATA
gogaku_dl-0.1.1.dist-info/WHEEL
gogaku_dl-0.1.1.dist-info/RECORD
