Metadata-Version: 2.1
Name: gogaku_dl
Version: 0.1.1
Summary: 
Home-page: https://github.com/takushi1969/gogaku_dl
License: MIT
Author: Takushi Usami
Author-email: takushi1969@gmail.com
Requires-Python: >=3.12,<4.0
Classifier: License :: OSI Approved :: MIT License
Classifier: Programming Language :: Python :: 3
Classifier: Programming Language :: Python :: 3.12
Requires-Dist: beautifulsoup4 (>=4.12,<5.0)
Requires-Dist: requests (>=2.32,<3.0)
